{    
	"combat.check_fatigue": true,
    "combat.check_lbas_fatigue": true,
    "combat.clear_stop": false,
    "combat.enabled": false,
    "combat.fleet_mode": "standard",
    "combat.fleet_presets": [],
    "combat.lbas_group_1_nodes": [],
    "combat.lbas_group_2_nodes": [],
    "combat.lbas_group_3_nodes": [],
    "combat.lbas_groups": [],
    "combat.node_formations": [],
    "combat.node_night_battles": [],
    "combat.node_selects": [],
    "combat.override": false,
    "combat.port_check": false,
    "combat.push_nodes": [],
    "combat.repair_limit": 3,
    "combat.repair_timelimit_hours": 0,
    "combat.repair_timelimit_minutes": 0,
    "combat.reserve_repair_dock": true,
    "combat.retreat_limit": 4,
    "combat.retreat_points": [],
    "combat.sortie_map": "1-1",
    "event_reset.enabled": false,
    "event_reset.farm_difficulty": 2,
    "event_reset.frequency": 3,
    "event_reset.reset_difficulty": 3,
    "expedition.enabled": true,
    "expedition.fleet_2": [],
    "expedition.fleet_3": [],
    "expedition.fleet_4": [],
    "expedition.fleet_preset": null,
    "factory.build_recipe": [
        30,
        30,
        30,
        30
    ],
    "factory.build_secretary": 0,
    "factory.develop_recipe": [
        20,
        60,
        10,
        110
    ],
    "factory.develop_secretary": 0,
    "factory.enabled": false,
    "general.chrome_dev_port": 9222,
    "general.interaction_mode": "chrome_driver",
    "general.jst_offset": 0,
    "general.paused": false,
    "passive_repair.enabled": true,
    "passive_repair.repair_threshold": 1,
    "passive_repair.slots_to_reserve": 0,
    "pvp.enabled": false,
    "pvp.fleet_preset": 0,
    "quest.enabled": true,
    "quest.quests": [
        "Bd1",
        "Bd2",
        "Bd3",
        "Bd4",
        "Bd5",
        "Bd6",
        "Bd7",
        "Bd8",
        "Bw1",
        "Bw2",
        "Bw3",
        "Bw4",
        "Bw5",
        "Bw7",
        "Bw8",
        "Bw9",
        "Bw10",
        "Bm2",
        "Bm3",
        "Bm4",
        "Bm5",
        "Bm6",
        "Bm8",
        "Bq1",
        "Bq3",
        "Bq4",
        "Bq5",
        "Bq6",
        "Bq8",
        "Bq9",
        "Bq11",
        "Bq12",
        "By2",
        "By3",
        "By4",
        "By6",
        "By7",
        "By8",
        "By9",
        "C2",
        "C3",
        "C4",
        "C8",
        "C16",
        "C29",
        "D2",
        "D3",
        "D4",
        "D9",
        "D11",
        "D22",
        "D24",
        "E3",
        "E4",
        "F5",
        "F6",
        "F7",
        "F8"
    ],
    "scheduler.enabled": true,
    "scheduler.rules": [
        "time:0230:stop:kcauto",
        "sorties_run:10:stop:combat"
    ],
    "ship_switcher.enabled": true,
    "ship_switcher.slots": {
        "1": "morale:!=:0|ship:187:>=:1:>=:0:!=:0::",
        "2": "damage:==:0,damage:>=:3|class:1:!=:1:==:1:!=:0::,class:1:!=:1:==:2:!=:0::,class:2:!=:1:==:1:!=:0::,class:2:!=:1:==:2:!=:0::,class:3:!=:1:==:1:!=:0::,class:3:!=:1:==:2:!=:0::,class:4:!=:1:==:1:!=:0::,class:4:!=:1:==:2:!=:0::,class:5:!=:1:==:1:!=:0::,class:5:!=:1:==:2:!=:0::,class:6:!=:1:==:1:!=:0::,class:6:!=:1:==:2:!=:0::,class:7:!=:1:==:1:!=:0::,class:7:!=:1:==:2:!=:0::,class:8:!=:1:==:1:!=:0::,class:8:!=:1:==:2:!=:0::,class:9:!=:1:==:1:!=:0::,class:9:!=:1:==:2:!=:0::,class:10:!=:1:==:1:!=:0::,class:10:!=:1:==:2:!=:0::,class:11:!=:1:==:1:!=:0::,class:11:!=:1:==:2:!=:0::,class:13:!=:1:==:1:!=:0::,class:13:!=:1:==:2:!=:0::,class:14:!=:1:==:1:!=:0::,class:14:!=:1:==:2:!=:0::,class:16:!=:1:==:1:!=:0::,class:16:!=:1:==:2:!=:0::,class:17:!=:1:==:1:!=:0::,class:17:!=:1:==:2:!=:0::,class:18:!=:1:==:1:!=:0::,class:18:!=:1:==:2:!=:0::,class:19:!=:1:==:1:!=:0::,class:19:!=:1:==:2:!=:0::,class:20:!=:1:==:1:!=:0::,class:20:!=:1:==:2:!=:0::,class:21:!=:1:==:1:!=:0::,class:21:!=:1:==:2:!=:0::,class:22:!=:1:==:1:!=:0::,class:22:!=:1:==:2:!=:0::",
        "3": "damage:==:0,damage:>=:3|class:1:!=:1:==:1:!=:0::,class:1:!=:1:==:2:!=:0::,class:2:!=:1:==:1:!=:0::,class:2:!=:1:==:2:!=:0::,class:3:!=:1:==:1:!=:0::,class:3:!=:1:==:2:!=:0::,class:4:!=:1:==:1:!=:0::,class:4:!=:1:==:2:!=:0::,class:5:!=:1:==:1:!=:0::,class:5:!=:1:==:2:!=:0::,class:6:!=:1:==:1:!=:0::,class:6:!=:1:==:2:!=:0::,class:7:!=:1:==:1:!=:0::,class:7:!=:1:==:2:!=:0::,class:8:!=:1:==:1:!=:0::,class:8:!=:1:==:2:!=:0::,class:9:!=:1:==:1:!=:0::,class:9:!=:1:==:2:!=:0::,class:10:!=:1:==:1:!=:0::,class:10:!=:1:==:2:!=:0::,class:11:!=:1:==:1:!=:0::,class:11:!=:1:==:2:!=:0::,class:13:!=:1:==:1:!=:0::,class:13:!=:1:==:2:!=:0::,class:14:!=:1:==:1:!=:0::,class:14:!=:1:==:2:!=:0::,class:16:!=:1:==:1:!=:0::,class:16:!=:1:==:2:!=:0::,class:17:!=:1:==:1:!=:0::,class:17:!=:1:==:2:!=:0::,class:18:!=:1:==:1:!=:0::,class:18:!=:1:==:2:!=:0::,class:19:!=:1:==:1:!=:0::,class:19:!=:1:==:2:!=:0::,class:20:!=:1:==:1:!=:0::,class:20:!=:1:==:2:!=:0::,class:21:!=:1:==:1:!=:0::,class:21:!=:1:==:2:!=:0::,class:22:!=:1:==:1:!=:0::,class:22:!=:1:==:2:!=:0::",
        "4": "damage:==:0,damage:>=:3|class:1:!=:1:==:1:!=:0::,class:1:!=:1:==:2:!=:0::,class:2:!=:1:==:1:!=:0::,class:2:!=:1:==:2:!=:0::,class:3:!=:1:==:1:!=:0::,class:3:!=:1:==:2:!=:0::,class:4:!=:1:==:1:!=:0::,class:4:!=:1:==:2:!=:0::,class:5:!=:1:==:1:!=:0::,class:5:!=:1:==:2:!=:0::,class:6:!=:1:==:1:!=:0::,class:6:!=:1:==:2:!=:0::,class:7:!=:1:==:1:!=:0::,class:7:!=:1:==:2:!=:0::,class:8:!=:1:==:1:!=:0::,class:8:!=:1:==:2:!=:0::,class:9:!=:1:==:1:!=:0::,class:9:!=:1:==:2:!=:0::,class:10:!=:1:==:1:!=:0::,class:10:!=:1:==:2:!=:0::,class:11:!=:1:==:1:!=:0::,class:11:!=:1:==:2:!=:0::,class:13:!=:1:==:1:!=:0::,class:13:!=:1:==:2:!=:0::,class:14:!=:1:==:1:!=:0::,class:14:!=:1:==:2:!=:0::,class:16:!=:1:==:1:!=:0::,class:16:!=:1:==:2:!=:0::,class:17:!=:1:==:1:!=:0::,class:17:!=:1:==:2:!=:0::,class:18:!=:1:==:1:!=:0::,class:18:!=:1:==:2:!=:0::,class:19:!=:1:==:1:!=:0::,class:19:!=:1:==:2:!=:0::,class:20:!=:1:==:1:!=:0::,class:20:!=:1:==:2:!=:0::,class:21:!=:1:==:1:!=:0::,class:21:!=:1:==:2:!=:0::,class:22:!=:1:==:1:!=:0::,class:22:!=:1:==:2:!=:0::",
        "5": "damage:==:0,damage:>=:3|class:1:!=:1:==:1:!=:0::,class:1:!=:1:==:2:!=:0::,class:2:!=:1:==:1:!=:0::,class:2:!=:1:==:2:!=:0::,class:3:!=:1:==:1:!=:0::,class:3:!=:1:==:2:!=:0::,class:4:!=:1:==:1:!=:0::,class:4:!=:1:==:2:!=:0::,class:5:!=:1:==:1:!=:0::,class:5:!=:1:==:2:!=:0::,class:6:!=:1:==:1:!=:0::,class:6:!=:1:==:2:!=:0::,class:7:!=:1:==:1:!=:0::,class:7:!=:1:==:2:!=:0::,class:8:!=:1:==:1:!=:0::,class:8:!=:1:==:2:!=:0::,class:9:!=:1:==:1:!=:0::,class:9:!=:1:==:2:!=:0::,class:10:!=:1:==:1:!=:0::,class:10:!=:1:==:2:!=:0::,class:11:!=:1:==:1:!=:0::,class:11:!=:1:==:2:!=:0::,class:13:!=:1:==:1:!=:0::,class:13:!=:1:==:2:!=:0::,class:14:!=:1:==:1:!=:0::,class:14:!=:1:==:2:!=:0::,class:16:!=:1:==:1:!=:0::,class:16:!=:1:==:2:!=:0::,class:17:!=:1:==:1:!=:0::,class:17:!=:1:==:2:!=:0::,class:18:!=:1:==:1:!=:0::,class:18:!=:1:==:2:!=:0::,class:19:!=:1:==:1:!=:0::,class:19:!=:1:==:2:!=:0::,class:20:!=:1:==:1:!=:0::,class:20:!=:1:==:2:!=:0::,class:21:!=:1:==:1:!=:0::,class:21:!=:1:==:2:!=:0::,class:22:!=:1:==:1:!=:0::,class:22:!=:1:==:2:!=:0::",
        "6": "damage:==:0,damage:>=:3|class:1:!=:1:==:1:!=:0::,class:1:!=:1:==:2:!=:0::,class:2:!=:1:==:1:!=:0::,class:2:!=:1:==:2:!=:0::,class:3:!=:1:==:1:!=:0::,class:3:!=:1:==:2:!=:0::,class:4:!=:1:==:1:!=:0::,class:4:!=:1:==:2:!=:0::,class:5:!=:1:==:1:!=:0::,class:5:!=:1:==:2:!=:0::,class:6:!=:1:==:1:!=:0::,class:6:!=:1:==:2:!=:0::,class:7:!=:1:==:1:!=:0::,class:7:!=:1:==:2:!=:0::,class:8:!=:1:==:1:!=:0::,class:8:!=:1:==:2:!=:0::,class:9:!=:1:==:1:!=:0::,class:9:!=:1:==:2:!=:0::,class:10:!=:1:==:1:!=:0::,class:10:!=:1:==:2:!=:0::,class:11:!=:1:==:1:!=:0::,class:11:!=:1:==:2:!=:0::,class:13:!=:1:==:1:!=:0::,class:13:!=:1:==:2:!=:0::,class:14:!=:1:==:1:!=:0::,class:14:!=:1:==:2:!=:0::,class:16:!=:1:==:1:!=:0::,class:16:!=:1:==:2:!=:0::,class:17:!=:1:==:1:!=:0::,class:17:!=:1:==:2:!=:0::,class:18:!=:1:==:1:!=:0::,class:18:!=:1:==:2:!=:0::,class:19:!=:1:==:1:!=:0::,class:19:!=:1:==:2:!=:0::,class:20:!=:1:==:1:!=:0::,class:20:!=:1:==:2:!=:0::,class:21:!=:1:==:1:!=:0::,class:21:!=:1:==:2:!=:0::,class:22:!=:1:==:1:!=:0::,class:22:!=:1:==:2:!=:0::"
    }
}